<?xml version="1.0" encoding="utf-8" ?>
<dwsync>
<file name="034.jpg" server="ftp.reynoldsconsultinganddesign.com" local="130144897080311392" remote="130034767800000000" Dst="2" />
<file name="046.jpg" server="ftp.reynoldsconsultinganddesign.com" local="130144897082611395" remote="130034767800000000" Dst="2" />
<file name="047.jpg" server="ftp.reynoldsconsultinganddesign.com" local="130144897084411398" remote="130034767800000000" Dst="2" />
<file name="048.jpg" server="ftp.reynoldsconsultinganddesign.com" local="130144897085811400" remote="130034767800000000" Dst="2" />
<file name="049.jpg" server="ftp.reynoldsconsultinganddesign.com" local="130144897087711402" remote="130034767800000000" Dst="2" />
<file name="050.jpg" server="ftp.reynoldsconsultinganddesign.com" local="130144897088511403" remote="130034767800000000" Dst="2" />
<file name="051.jpg" server="ftp.reynoldsconsultinganddesign.com" local="130144897090521407" remote="130034767800000000" Dst="2" />
<file name="052.jpg" server="ftp.reynoldsconsultinganddesign.com" local="130144897092421409" remote="130034767800000000" Dst="2" />
<file name="055.jpg" server="ftp.reynoldsconsultinganddesign.com" local="130144897093821411" remote="130034767800000000" Dst="2" />
<file name="549.jpg" server="ftp.reynoldsconsultinganddesign.com" local="130144897095421414" remote="130034767800000000" Dst="2" />
<file name="550.jpg" server="ftp.reynoldsconsultinganddesign.com" local="130144897096821415" remote="130034767800000000" Dst="2" />
<file name="551.jpg" server="ftp.reynoldsconsultinganddesign.com" local="130144897098321418" remote="130034767800000000" Dst="2" />
</dwsync>